

Loading class REDApp ...

  0001: Class - 0071
  0002: MethodRef - Class=001E, Name&Type=0072
  0003: MethodRef - Class=0073, Name&Type=0074
  0004: MethodRef - Class=0073, Name&Type=0075
  0005: MethodRef - Class=0073, Name&Type=0076
  0006: MethodRef - Class=0073, Name&Type=0077
  0007: MethodRef - Class=0073, Name&Type=0078
  0008: MethodRef - Class=0073, Name&Type=0079
  0009: FieldRef - Class=0001, Name&Type=007A
  000A: MethodRef - Class=0001, Name&Type=007B
  000B: FieldRef - Class=0001, Name&Type=007C
  000C: FieldRef - Class=001C, Name&Type=007D
  000D: MethodRef - Class=007E, Name&Type=007F
  000E: FieldRef - Class=001C, Name&Type=0080
  000F: MethodRef - Class=007E, Name&Type=0081
  0010: FieldRef - Class=0001, Name&Type=0082
  0011: FieldRef - Class=0001, Name&Type=0083
  0012: MethodRef - Class=0001, Name&Type=0084
  0013: FieldRef - Class=001C, Name&Type=0085
  0014: FieldRef - Class=001C, Name&Type=0086
  0015: FieldRef - Class=001C, Name&Type=0087
  0016: MethodRef - Class=0001, Name&Type=0088
  0017: FieldRef - Class=0001, Name&Type=0089
  0018: FieldRef - Class=0001, Name&Type=008A
  0019: FieldRef - Class=0001, Name&Type=008B
  001A: FieldRef - Class=0001, Name&Type=008C
  001B: FieldRef - Class=0001, Name&Type=008D
  001C: Class - 008E
  001D: MethodRef - Class=001C, Name&Type=0072
  001E: Class - 008F
  001F: UTF8 - Tag
  0020: UTF8 - InnerClasses
  0021: UTF8 - isDebug
  0022: UTF8 - Z
  0023: UTF8 - ConstantValue
  0024: Integer - 00000000
  0025: UTF8 - PubKS
  0026: UTF8 - [B
  0027: UTF8 - InvalidTagNo
  0028: UTF8 - B
  0029: Integer - 0000007F
  002A: UTF8 - TagInfoLen
  002B: Integer - 00000023
  002C: UTF8 - PubKlen
  002D: Integer - 00000048
  002E: UTF8 - SIGlen
  002F: UTF8 - RNDlen
  0030: Integer - 00000008
  0031: UTF8 - WeightLen
  0032: Integer - 00000004
  0033: UTF8 - CertLen
  0034: UTF8 - S
  0035: Integer - 000000B5
  0036: UTF8 - PubKCoffset
  0037: UTF8 - CertSIGoffset
  0038: Integer - 0000006B
  0039: UTF8 - SignedWeightLen
  003A: Integer - 00000066
  003B: UTF8 - WeightSIGoffset
  003C: Integer - 0000001C
  003D: UTF8 - WeightRNDoffset
  003E: Integer - 00000010
  003F: UTF8 - WeightOffset
  0040: Integer - 00000018
  0041: UTF8 - ActiveTagsLen
  0042: UTF8 - TagNoMin
  0043: UTF8 - TagNoMax
  0044: Integer - 0000000F
  0045: UTF8 - signedChallengeLen
  0046: Integer - 0000006A
  0047: UTF8 - challengeOffset
  0048: UTF8 - signedChallengeMessgeLen
  0049: Integer - 00000020
  004A: UTF8 - signedChallengeSignatureOffset
  004B: Integer - 00000022
  004C: UTF8 - tags
  004D: UTF8 - [LREDApp$Tag;
  004E: UTF8 - isValid
  004F: UTF8 - tagRandom
  0050: UTF8 - lastTagNo
  0051: UTF8 - lastIsActive
  0052: UTF8 - Slices
  0053: UTF8 - message
  0054: UTF8 - signature
  0055: UTF8 - <init>
  0056: UTF8 - ()V
  0057: UTF8 - Code
  0058: UTF8 - verifyMessage
  0059: UTF8 - ([B[B[B)Z
  005A: UTF8 - StackMapTable
  005B: Class - 0026
  005C: UTF8 - generateRandom
  005D: UTF8 - ([B)V
  005E: UTF8 - verifyTag
  005F: UTF8 - (BZ[B[B)Z
  0060: UTF8 - verifyChallenge
  0061: UTF8 - (BZ[B)Z
  0062: UTF8 - removeTag
  0063: UTF8 - (B)Z
  0064: UTF8 - updateConsumption
  0065: UTF8 - (BZI[B)Z
  0066: UTF8 - verifyWeight
  0067: UTF8 - CNOF
  0068: UTF8 - (IIIII)I
  0069: UTF8 - CEOP
  006A: UTF8 - (IIIIII)I
  006B: UTF8 - CNOP
  006C: UTF8 - CYSO
  006D: UTF8 - (IIIIIIIII)I
  006E: UTF8 - getTagIndex
  006F: UTF8 - (BZ)B
  0070: UTF8 - <clinit>
  0071: UTF8 - REDApp
  0072: Name&Type - Name=0055, Desc=0056
  0073: Class - 0090
  0074: Name&Type - Name=0091, Desc=0056
  0075: Name&Type - Name=0092, Desc=005D
  0076: Name&Type - Name=0093, Desc=005D
  0077: Name&Type - Name=0094, Desc=0095
  0078: Name&Type - Name=0096, Desc=0097
  0079: Name&Type - Name=0098, Desc=0099
  007A: Name&Type - Name=004F, Desc=0026
  007B: Name&Type - Name=006E, Desc=006F
  007C: Name&Type - Name=004C, Desc=004D
  007D: Name&Type - Name=009A, Desc=0026
  007E: Class - 009B
  007F: Name&Type - Name=009C, Desc=009D
  0080: Name&Type - Name=009E, Desc=0022
  0081: Name&Type - Name=009F, Desc=00A0
  0082: Name&Type - Name=0054, Desc=0026
  0083: Name&Type - Name=0025, Desc=0026
  0084: Name&Type - Name=0058, Desc=0059
  0085: Name&Type - Name=00A1, Desc=0028
  0086: Name&Type - Name=00A2, Desc=00A3
  0087: Name&Type - Name=00A4, Desc=00A3
  0088: Name&Type - Name=005C, Desc=005D
  0089: Name&Type - Name=0050, Desc=0028
  008A: Name&Type - Name=0051, Desc=0022
  008B: Name&Type - Name=0053, Desc=0026
  008C: Name&Type - Name=004E, Desc=0022
  008D: Name&Type - Name=0052, Desc=0028
  008E: UTF8 - REDApp$Tag
  008F: UTF8 - java/lang/Object
  0090: UTF8 - token/classes/Crypto
  0091: UTF8 - sha256Init
  0092: UTF8 - sha256Update
  0093: UTF8 - sha256Finish
  0094: UTF8 - k283VerifyMessage
  0095: UTF8 - ([B[B[B)I
  0096: UTF8 - rand
  0097: UTF8 - ()I
  0098: UTF8 - genRandom
  0099: UTF8 - ([BII)V
  009A: UTF8 - pubKC
  009B: UTF8 - token/classes/Sys
  009C: UTF8 - memCmp
  009D: UTF8 - ([BI[BII)Z
  009E: UTF8 - isTagValid
  009F: UTF8 - memCpy
  00A0: UTF8 - ([BI[BII)V
  00A1: UTF8 - tagNo
  00A2: UTF8 - tagWeight
  00A3: UTF8 - I
  00A4: UTF8 - tagConsumption

Class REDApp contains 30 fields.

     0 - 0018 0002 00 0  S:0000 isDebug Z
     1 - 001A 8000 01 2  S:0000 PubKS [B
     2 - 001A 0002 00 0  S:0000 InvalidTagNo B
     3 - 001A 0002 00 0  S:0000 TagInfoLen B
     4 - 001A 0002 00 0  S:0000 PubKlen B
     5 - 001A 0002 00 0  S:0000 SIGlen B
     6 - 001A 0002 00 0  S:0000 RNDlen B
     7 - 001A 0002 00 0  S:0000 WeightLen B
     8 - 001A 0002 00 0  S:0000 CertLen S
     9 - 001A 0002 00 0  S:0000 PubKCoffset S
    10 - 001A 0002 00 0  S:0000 CertSIGoffset S
    11 - 001A 0002 00 0  S:0000 SignedWeightLen S
    12 - 001A 0002 00 0  S:0000 WeightSIGoffset S
    13 - 001A 0002 00 0  S:0000 WeightRNDoffset S
    14 - 001A 0002 00 0  S:0000 WeightOffset S
    15 - 001A 0002 00 0  S:0000 ActiveTagsLen B
    16 - 001A 0002 00 0  S:0000 TagNoMin B
    17 - 001A 0002 00 0  S:0000 TagNoMax B
    18 - 001A 0002 00 0  S:0000 signedChallengeLen S
    19 - 001A 0002 00 0  S:0000 challengeOffset S
    20 - 001A 0002 00 0  S:0000 signedChallengeMessgeLen S
    21 - 001A 0002 00 0  S:0000 signedChallengeSignatureOffset S
    22 - 000A 8000 20 2  S:0002 tags [LREDApp$Tag;
    23 - 000A 0000 00 1  S:0004 isValid Z
    24 - 000A 8000 01 2  S:0005 tagRandom [B
    25 - 000A 0000 01 1  S:0007 lastTagNo B
    26 - 000A 0000 00 1  S:0008 lastIsActive Z
    27 - 000A 0000 01 1  S:0009 Slices B
    28 - 000A 8000 01 2  S:000A message [B
    29 - 000A 8000 01 2  S:000C signature [B

Method: REDApp.<init> : ()V

MaxStack ............... 1
MaxLocals .............. 1
Access Flags ........... 2001
Code Size .............. 5

 0000: 2A  aload_0
 0001: B7  invokespecial 2 java/lang/Object.<init> : ()V
 0004: B1  return

Method: REDApp.verifyMessage : ([B[B[B)Z

MaxStack ............... 3
MaxLocals .............. 4
Access Flags ........... a
Code Size .............. 31

 0000: 10  bipush 32
 0002: BC  newarray 8
 0004: 4E  astore_3
 0005: B8  invokestatic 3 token/classes/Crypto.sha256Init : ()V
 0008: 2B  aload_1
 0009: B8  invokestatic 4 token/classes/Crypto.sha256Update : ([B)V
 000C: 2D  aload_3
 000D: B8  invokestatic 5 token/classes/Crypto.sha256Finish : ([B)V
 0010: 2D  aload_3
 0011: 2C  aload_2
 0012: 2A  aload_0
 0013: B8  invokestatic 6 token/classes/Crypto.k283VerifyMessage : ([B[B[B)I
 0016: 9A  ifne 001D
 0019: 04  iconst_1
 001A: A7  goto 001E
 001D: 03  iconst_0
 001E: AC  ireturn

Method: REDApp.generateRandom : ([B)V

MaxStack ............... 3
MaxLocals .............. 1
Access Flags ........... a
Code Size .............. 12

 0000: B8  invokestatic 7 token/classes/Crypto.rand : ()I
 0003: 57  pop
 0004: 2A  aload_0
 0005: 03  iconst_0
 0006: 2A  aload_0
 0007: BE  arraylength
 0008: B8  invokestatic 8 token/classes/Crypto.genRandom : ([BII)V
 000B: B1  return

Method: REDApp.verifyTag : (BZ[B[B)Z

MaxStack ............... 5
MaxLocals .............. 7
Access Flags ........... 9
Code Size .............. 267

 0000: 1A  iload_0
 0001: 9B  iflt 000A
 0004: 1A  iload_0
 0005: 10  bipush 15
 0007: A4  if_icmple 000C
 000A: 03  iconst_0
 000B: AC  ireturn
 000C: 2C  aload_2
 000D: C6  ifnull 0018
 0010: 2C  aload_2
 0011: BE  arraylength
 0012: 11  sipush 181
 0015: 9F  if_icmpeq 001A
 0018: 03  iconst_0
 0019: AC  ireturn
 001A: 2D  aload_3
 001B: C6  ifnull 0027
 001E: 2D  aload_3
 001F: BE  arraylength
 0020: B2  getstatic 9 REDApp.tagRandom : [B
 0023: BE  arraylength
 0024: 9F  if_icmpeq 0029
 0027: 03  iconst_0
 0028: AC  ireturn
 0029: 1A  iload_0
 002A: 1B  iload_1
 002B: B8  invokestatic 10 REDApp.getTagIndex : (BZ)B
 002E: 36  istore 4
 0030: 15  iload 4
 0032: 9E  ifle 004C
 0035: B2  getstatic 11 REDApp.tags : [LREDApp$Tag;
 0038: 15  iload 4
 003A: 32  aaload
 003B: B4  getfield 12 REDApp$Tag.pubKC : [B
 003E: 03  iconst_0
 003F: 2C  aload_2
 0040: 10  bipush 35
 0042: 10  bipush 72
 0044: B8  invokestatic 13 token/classes/Sys.memCmp : ([BI[BII)Z
 0047: 9A  ifne 004C
 004A: 03  iconst_0
 004B: AC  ireturn
 004C: 15  iload 4
 004E: 9C  ifge 0060
 0051: 10  bipush 127
 0053: 04  iconst_1
 0054: B8  invokestatic 10 REDApp.getTagIndex : (BZ)B
 0057: 36  istore 4
 0059: 15  iload 4
 005B: 9C  ifge 0060
 005E: 03  iconst_0
 005F: AC  ireturn
 0060: B2  getstatic 11 REDApp.tags : [LREDApp$Tag;
 0063: 15  iload 4
 0065: 32  aaload
 0066: 03  iconst_0
 0067: B5  putfield 14 REDApp$Tag.isTagValid : Z
 006A: B2  getstatic 11 REDApp.tags : [LREDApp$Tag;
 006D: 15  iload 4
 006F: 32  aaload
 0070: B4  getfield 12 REDApp$Tag.pubKC : [B
 0073: 03  iconst_0
 0074: 2C  aload_2
 0075: 10  bipush 35
 0077: 10  bipush 72
 0079: B8  invokestatic 15 token/classes/Sys.memCpy : ([BI[BII)V
 007C: 2C  aload_2
 007D: 10  bipush 108
 007F: 33  baload
 0080: 11  sipush 255
 0083: 7E  iand
 0084: 10  bipush 8
 0086: 78  ishl
 0087: 2C  aload_2
 0088: 10  bipush 107
 008A: 33  baload
 008B: 11  sipush 255
 008E: 7E  iand
 008F: 80  ior
 0090: 93  i2s
 0091: 36  istore 5
 0093: 15  iload 5
 0095: 10  bipush 72
 0097: 9F  if_icmpeq 009C
 009A: 03  iconst_0
 009B: AC  ireturn
 009C: B2  getstatic 16 REDApp.signature : [B
 009F: 03  iconst_0
 00A0: 2C  aload_2
 00A1: 10  bipush 109
 00A3: 10  bipush 72
 00A5: B8  invokestatic 15 token/classes/Sys.memCpy : ([BI[BII)V
 00A8: 10  bipush 107
 00AA: BC  newarray 8
 00AC: 3A  astore 6
 00AE: 19  aload 6
 00B0: 03  iconst_0
 00B1: 2C  aload_2
 00B2: 03  iconst_0
 00B3: 10  bipush 107
 00B5: B8  invokestatic 15 token/classes/Sys.memCpy : ([BI[BII)V
 00B8: B2  getstatic 17 REDApp.PubKS : [B
 00BB: 19  aload 6
 00BD: B2  getstatic 16 REDApp.signature : [B
 00C0: B8  invokestatic 18 REDApp.verifyMessage : ([B[B[B)Z
 00C3: 9A  ifne 00C8
 00C6: 03  iconst_0
 00C7: AC  ireturn
 00C8: B2  getstatic 11 REDApp.tags : [LREDApp$Tag;
 00CB: 15  iload 4
 00CD: 32  aaload
 00CE: 1A  iload_0
 00CF: B5  putfield 19 REDApp$Tag.tagNo : B
 00D2: B2  getstatic 11 REDApp.tags : [LREDApp$Tag;
 00D5: 15  iload 4
 00D7: 32  aaload
 00D8: 02  iconst_m1
 00D9: B5  putfield 20 REDApp$Tag.tagWeight : I
 00DC: B2  getstatic 11 REDApp.tags : [LREDApp$Tag;
 00DF: 15  iload 4
 00E1: 32  aaload
 00E2: 03  iconst_0
 00E3: B5  putfield 21 REDApp$Tag.tagConsumption : I
 00E6: B2  getstatic 9 REDApp.tagRandom : [B
 00E9: B8  invokestatic 22 REDApp.generateRandom : ([B)V
 00EC: 2D  aload_3
 00ED: 03  iconst_0
 00EE: B2  getstatic 9 REDApp.tagRandom : [B
 00F1: 03  iconst_0
 00F2: 10  bipush 8
 00F4: B8  invokestatic 15 token/classes/Sys.memCpy : ([BI[BII)V
 00F7: 1A  iload_0
 00F8: B3  putstatic 23 REDApp.lastTagNo : B
 00FB: 1B  iload_1
 00FC: B3  putstatic 24 REDApp.lastIsActive : Z
 00FF: B2  getstatic 11 REDApp.tags : [LREDApp$Tag;
 0102: 15  iload 4
 0104: 32  aaload
 0105: 04  iconst_1
 0106: B5  putfield 14 REDApp$Tag.isTagValid : Z
 0109: 04  iconst_1
 010A: AC  ireturn

Method: REDApp.verifyChallenge : (BZ[B)Z

MaxStack ............... 5
MaxLocals .............. 5
Access Flags ........... 9
Code Size .............. 130

 0000: 1A  iload_0
 0001: 9B  iflt 000A
 0004: 1A  iload_0
 0005: 10  bipush 15
 0007: A4  if_icmple 000C
 000A: 03  iconst_0
 000B: AC  ireturn
 000C: 2C  aload_2
 000D: BE  arraylength
 000E: 10  bipush 106
 0010: 9F  if_icmpeq 0015
 0013: 03  iconst_0
 0014: AC  ireturn
 0015: 1A  iload_0
 0016: 1B  iload_1
 0017: B8  invokestatic 10 REDApp.getTagIndex : (BZ)B
 001A: 3E  istore_3
 001B: 1D  iload_3
 001C: 9C  ifge 0021
 001F: 03  iconst_0
 0020: AC  ireturn
 0021: B2  getstatic 11 REDApp.tags : [LREDApp$Tag;
 0024: 1D  iload_3
 0025: 32  aaload
 0026: B4  getfield 14 REDApp$Tag.isTagValid : Z
 0029: 9A  ifne 002E
 002C: 03  iconst_0
 002D: AC  ireturn
 002E: 1A  iload_0
 002F: B2  getstatic 23 REDApp.lastTagNo : B
 0032: A0  if_icmpne 003C
 0035: 1B  iload_1
 0036: B2  getstatic 24 REDApp.lastIsActive : Z
 0039: 9F  if_icmpeq 003E
 003C: 03  iconst_0
 003D: AC  ireturn
 003E: B2  getstatic 9 REDApp.tagRandom : [B
 0041: 03  iconst_0
 0042: 2C  aload_2
 0043: 10  bipush 8
 0045: 10  bipush 8
 0047: B8  invokestatic 13 token/classes/Sys.memCmp : ([BI[BII)Z
 004A: 9A  ifne 004F
 004D: 03  iconst_0
 004E: AC  ireturn
 004F: 10  bipush 32
 0051: BC  newarray 8
 0053: 3A  astore 4
 0055: 19  aload 4
 0057: 03  iconst_0
 0058: 2C  aload_2
 0059: 03  iconst_0
 005A: 10  bipush 32
 005C: B8  invokestatic 15 token/classes/Sys.memCpy : ([BI[BII)V
 005F: B2  getstatic 16 REDApp.signature : [B
 0062: 03  iconst_0
 0063: 2C  aload_2
 0064: 10  bipush 34
 0066: 10  bipush 72
 0068: B8  invokestatic 15 token/classes/Sys.memCpy : ([BI[BII)V
 006B: B2  getstatic 11 REDApp.tags : [LREDApp$Tag;
 006E: 1D  iload_3
 006F: 32  aaload
 0070: B4  getfield 12 REDApp$Tag.pubKC : [B
 0073: 19  aload 4
 0075: B2  getstatic 16 REDApp.signature : [B
 0078: B8  invokestatic 18 REDApp.verifyMessage : ([B[B[B)Z
 007B: 9A  ifne 0080
 007E: 03  iconst_0
 007F: AC  ireturn
 0080: 04  iconst_1
 0081: AC  ireturn

Method: REDApp.removeTag : (B)Z

MaxStack ............... 2
MaxLocals .............. 2
Access Flags ........... 9
Code Size .............. 45

 0000: 1A  iload_0
 0001: 9B  iflt 000A
 0004: 1A  iload_0
 0005: 10  bipush 15
 0007: A4  if_icmple 000C
 000A: 03  iconst_0
 000B: AC  ireturn
 000C: 1A  iload_0
 000D: 04  iconst_1
 000E: B8  invokestatic 10 REDApp.getTagIndex : (BZ)B
 0011: 3C  istore_1
 0012: 1B  iload_1
 0013: 9C  ifge 0018
 0016: 03  iconst_0
 0017: AC  ireturn
 0018: B2  getstatic 11 REDApp.tags : [LREDApp$Tag;
 001B: 1B  iload_1
 001C: 32  aaload
 001D: 03  iconst_0
 001E: B5  putfield 14 REDApp$Tag.isTagValid : Z
 0021: B2  getstatic 11 REDApp.tags : [LREDApp$Tag;
 0024: 1B  iload_1
 0025: 32  aaload
 0026: 10  bipush 127
 0028: B5  putfield 19 REDApp$Tag.tagNo : B
 002B: 04  iconst_1
 002C: AC  ireturn

Method: REDApp.updateConsumption : (BZI[B)Z

MaxStack ............... 5
MaxLocals .............. 5
Access Flags ........... 9
Code Size .............. 92

 0000: 1A  iload_0
 0001: 9B  iflt 000A
 0004: 1A  iload_0
 0005: 10  bipush 15
 0007: A4  if_icmple 000C
 000A: 03  iconst_0
 000B: AC  ireturn
 000C: 2D  aload_3
 000D: C6  ifnull 0019
 0010: 2D  aload_3
 0011: BE  arraylength
 0012: B2  getstatic 9 REDApp.tagRandom : [B
 0015: BE  arraylength
 0016: 9F  if_icmpeq 001B
 0019: 03  iconst_0
 001A: AC  ireturn
 001B: 1A  iload_0
 001C: 1B  iload_1
 001D: B8  invokestatic 10 REDApp.getTagIndex : (BZ)B
 0020: 36  istore 4
 0022: 15  iload 4
 0024: 9C  ifge 0029
 0027: 03  iconst_0
 0028: AC  ireturn
 0029: B2  getstatic 11 REDApp.tags : [LREDApp$Tag;
 002C: 15  iload 4
 002E: 32  aaload
 002F: B4  getfield 14 REDApp$Tag.isTagValid : Z
 0032: 9A  ifne 0037
 0035: 03  iconst_0
 0036: AC  ireturn
 0037: B2  getstatic 11 REDApp.tags : [LREDApp$Tag;
 003A: 15  iload 4
 003C: 32  aaload
 003D: 1C  iload_2
 003E: B5  putfield 21 REDApp$Tag.tagConsumption : I
 0041: B2  getstatic 9 REDApp.tagRandom : [B
 0044: B8  invokestatic 22 REDApp.generateRandom : ([B)V
 0047: 2D  aload_3
 0048: 03  iconst_0
 0049: B2  getstatic 9 REDApp.tagRandom : [B
 004C: 03  iconst_0
 004D: 10  bipush 8
 004F: B8  invokestatic 15 token/classes/Sys.memCpy : ([BI[BII)V
 0052: 1A  iload_0
 0053: B3  putstatic 23 REDApp.lastTagNo : B
 0056: 1B  iload_1
 0057: B3  putstatic 24 REDApp.lastIsActive : Z
 005A: 04  iconst_1
 005B: AC  ireturn

Method: REDApp.verifyWeight : (BZ[B)Z

MaxStack ............... 5
MaxLocals .............. 6
Access Flags ........... 9
Code Size .............. 270

 0000: 1A  iload_0
 0001: 9B  iflt 000A
 0004: 1A  iload_0
 0005: 10  bipush 15
 0007: A4  if_icmple 000C
 000A: 03  iconst_0
 000B: AC  ireturn
 000C: 2C  aload_2
 000D: C6  ifnull 0017
 0010: 2C  aload_2
 0011: BE  arraylength
 0012: 10  bipush 102
 0014: 9F  if_icmpeq 0019
 0017: 03  iconst_0
 0018: AC  ireturn
 0019: 1A  iload_0
 001A: 1B  iload_1
 001B: B8  invokestatic 10 REDApp.getTagIndex : (BZ)B
 001E: 3E  istore_3
 001F: 1D  iload_3
 0020: 9C  ifge 0025
 0023: 03  iconst_0
 0024: AC  ireturn
 0025: B2  getstatic 11 REDApp.tags : [LREDApp$Tag;
 0028: 1D  iload_3
 0029: 32  aaload
 002A: B4  getfield 14 REDApp$Tag.isTagValid : Z
 002D: 9A  ifne 0032
 0030: 03  iconst_0
 0031: AC  ireturn
 0032: B2  getstatic 11 REDApp.tags : [LREDApp$Tag;
 0035: 1D  iload_3
 0036: 32  aaload
 0037: 03  iconst_0
 0038: B5  putfield 14 REDApp$Tag.isTagValid : Z
 003B: B2  getstatic 25 REDApp.message : [B
 003E: 03  iconst_0
 003F: 2C  aload_2
 0040: 03  iconst_0
 0041: 10  bipush 28
 0043: B8  invokestatic 15 token/classes/Sys.memCpy : ([BI[BII)V
 0046: 2C  aload_2
 0047: 10  bipush 29
 0049: 33  baload
 004A: 11  sipush 255
 004D: 7E  iand
 004E: 10  bipush 8
 0050: 78  ishl
 0051: 2C  aload_2
 0052: 10  bipush 28
 0054: 33  baload
 0055: 11  sipush 255
 0058: 7E  iand
 0059: 80  ior
 005A: 93  i2s
 005B: 36  istore 4
 005D: 15  iload 4
 005F: 10  bipush 72
 0061: 9F  if_icmpeq 0066
 0064: 03  iconst_0
 0065: AC  ireturn
 0066: B2  getstatic 16 REDApp.signature : [B
 0069: 03  iconst_0
 006A: 2C  aload_2
 006B: 10  bipush 30
 006D: 10  bipush 72
 006F: B8  invokestatic 15 token/classes/Sys.memCpy : ([BI[BII)V
 0072: B2  getstatic 11 REDApp.tags : [LREDApp$Tag;
 0075: 1D  iload_3
 0076: 32  aaload
 0077: B4  getfield 12 REDApp$Tag.pubKC : [B
 007A: B2  getstatic 25 REDApp.message : [B
 007D: B2  getstatic 16 REDApp.signature : [B
 0080: B8  invokestatic 18 REDApp.verifyMessage : ([B[B[B)Z
 0083: 9A  ifne 0088
 0086: 03  iconst_0
 0087: AC  ireturn
 0088: B2  getstatic 9 REDApp.tagRandom : [B
 008B: 03  iconst_0
 008C: 2C  aload_2
 008D: 10  bipush 16
 008F: B2  getstatic 9 REDApp.tagRandom : [B
 0092: BE  arraylength
 0093: B8  invokestatic 13 token/classes/Sys.memCmp : ([BI[BII)Z
 0096: 9A  ifne 009B
 0099: 03  iconst_0
 009A: AC  ireturn
 009B: 2C  aload_2
 009C: 10  bipush 27
 009E: 33  baload
 009F: 10  bipush 24
 00A1: 78  ishl
 00A2: 2C  aload_2
 00A3: 10  bipush 26
 00A5: 33  baload
 00A6: 11  sipush 255
 00A9: 7E  iand
 00AA: 10  bipush 16
 00AC: 78  ishl
 00AD: 80  ior
 00AE: 2C  aload_2
 00AF: 10  bipush 25
 00B1: 33  baload
 00B2: 11  sipush 255
 00B5: 7E  iand
 00B6: 10  bipush 8
 00B8: 78  ishl
 00B9: 80  ior
 00BA: 2C  aload_2
 00BB: 10  bipush 24
 00BD: 33  baload
 00BE: 11  sipush 255
 00C1: 7E  iand
 00C2: 80  ior
 00C3: 36  istore 5
 00C5: B2  getstatic 11 REDApp.tags : [LREDApp$Tag;
 00C8: 1D  iload_3
 00C9: 32  aaload
 00CA: B4  getfield 20 REDApp$Tag.tagWeight : I
 00CD: 02  iconst_m1
 00CE: 9F  if_icmpeq 00E9
 00D1: 15  iload 5
 00D3: B2  getstatic 11 REDApp.tags : [LREDApp$Tag;
 00D6: 1D  iload_3
 00D7: 32  aaload
 00D8: B4  getfield 20 REDApp$Tag.tagWeight : I
 00DB: B2  getstatic 11 REDApp.tags : [LREDApp$Tag;
 00DE: 1D  iload_3
 00DF: 32  aaload
 00E0: B4  getfield 21 REDApp$Tag.tagConsumption : I
 00E3: 64  isub
 00E4: 9F  if_icmpeq 00E9
 00E7: 03  iconst_0
 00E8: AC  ireturn
 00E9: B2  getstatic 11 REDApp.tags : [LREDApp$Tag;
 00EC: 1D  iload_3
 00ED: 32  aaload
 00EE: 15  iload 5
 00F0: B5  putfield 20 REDApp$Tag.tagWeight : I
 00F3: B2  getstatic 11 REDApp.tags : [LREDApp$Tag;
 00F6: 1D  iload_3
 00F7: 32  aaload
 00F8: 03  iconst_0
 00F9: B5  putfield 21 REDApp$Tag.tagConsumption : I
 00FC: 15  iload 5
 00FE: 9A  ifne 0103
 0101: 03  iconst_0
 0102: AC  ireturn
 0103: B2  getstatic 11 REDApp.tags : [LREDApp$Tag;
 0106: 1D  iload_3
 0107: 32  aaload
 0108: 04  iconst_1
 0109: B5  putfield 14 REDApp$Tag.isTagValid : Z
 010C: 04  iconst_1
 010D: AC  ireturn

Method: REDApp.CNOF : (IIIII)I

MaxStack ............... 2
MaxLocals .............. 7
Access Flags ........... 9
Code Size .............. 78

 0000: 10  bipush 100
 0002: 36  istore 5
 0004: B2  getstatic 26 REDApp.isValid : Z
 0007: 9A  ifne 000F
 000A: 15  iload 5
 000C: 05  iconst_2
 000D: 68  imul
 000E: AC  ireturn
 000F: B2  getstatic 27 REDApp.Slices : B
 0012: 04  iconst_1
 0013: 60  iadd
 0014: 91  i2b
 0015: B3  putstatic 27 REDApp.Slices : B
 0018: B2  getstatic 27 REDApp.Slices : B
 001B: 10  bipush 25
 001D: A4  if_icmple 0024
 0020: 03  iconst_0
 0021: B3  putstatic 26 REDApp.isValid : Z
 0024: 04  iconst_1
 0025: 36  istore 6
 0027: 15  iload 6
 0029: B2  getstatic 11 REDApp.tags : [LREDApp$Tag;
 002C: BE  arraylength
 002D: A2  if_icmpge 004B
 0030: B2  getstatic 11 REDApp.tags : [LREDApp$Tag;
 0033: 15  iload 6
 0035: 32  aaload
 0036: B4  getfield 14 REDApp$Tag.isTagValid : Z
 0039: 9A  ifne 0041
 003C: 15  iload 5
 003E: 06  iconst_3
 003F: 68  imul
 0040: AC  ireturn
 0041: 15  iload 6
 0043: 04  iconst_1
 0044: 60  iadd
 0045: 91  i2b
 0046: 36  istore 6
 0048: A7  goto 0027
 004B: 15  iload 5
 004D: AC  ireturn

Method: REDApp.CEOP : (IIIIII)I

MaxStack ............... 2
MaxLocals .............. 8
Access Flags ........... 9
Code Size .............. 58

 0000: 11  sipush 200
 0003: 36  istore 6
 0005: B2  getstatic 26 REDApp.isValid : Z
 0008: 9A  ifne 0010
 000B: 15  iload 6
 000D: 05  iconst_2
 000E: 68  imul
 000F: AC  ireturn
 0010: 04  iconst_1
 0011: 36  istore 7
 0013: 15  iload 7
 0015: B2  getstatic 11 REDApp.tags : [LREDApp$Tag;
 0018: BE  arraylength
 0019: A2  if_icmpge 0037
 001C: B2  getstatic 11 REDApp.tags : [LREDApp$Tag;
 001F: 15  iload 7
 0021: 32  aaload
 0022: B4  getfield 14 REDApp$Tag.isTagValid : Z
 0025: 9A  ifne 002D
 0028: 15  iload 6
 002A: 06  iconst_3
 002B: 68  imul
 002C: AC  ireturn
 002D: 15  iload 7
 002F: 04  iconst_1
 0030: 60  iadd
 0031: 91  i2b
 0032: 36  istore 7
 0034: A7  goto 0013
 0037: 15  iload 6
 0039: AC  ireturn

Method: REDApp.CNOP : (IIIIII)I

MaxStack ............... 2
MaxLocals .............. 8
Access Flags ........... 9
Code Size .............. 58

 0000: 11  sipush 300
 0003: 36  istore 6
 0005: B2  getstatic 26 REDApp.isValid : Z
 0008: 9A  ifne 0010
 000B: 15  iload 6
 000D: 05  iconst_2
 000E: 68  imul
 000F: AC  ireturn
 0010: 04  iconst_1
 0011: 36  istore 7
 0013: 15  iload 7
 0015: B2  getstatic 11 REDApp.tags : [LREDApp$Tag;
 0018: BE  arraylength
 0019: A2  if_icmpge 0037
 001C: B2  getstatic 11 REDApp.tags : [LREDApp$Tag;
 001F: 15  iload 7
 0021: 32  aaload
 0022: B4  getfield 14 REDApp$Tag.isTagValid : Z
 0025: 9A  ifne 002D
 0028: 15  iload 6
 002A: 06  iconst_3
 002B: 68  imul
 002C: AC  ireturn
 002D: 15  iload 7
 002F: 04  iconst_1
 0030: 60  iadd
 0031: 91  i2b
 0032: 36  istore 7
 0034: A7  goto 0013
 0037: 15  iload 6
 0039: AC  ireturn

Method: REDApp.CYSO : (IIIIIIIII)I

MaxStack ............... 2
MaxLocals .............. 11
Access Flags ........... 9
Code Size .............. 58

 0000: 11  sipush 400
 0003: 36  istore 9
 0005: B2  getstatic 26 REDApp.isValid : Z
 0008: 9A  ifne 0010
 000B: 15  iload 9
 000D: 05  iconst_2
 000E: 68  imul
 000F: AC  ireturn
 0010: 04  iconst_1
 0011: 36  istore 10
 0013: 15  iload 10
 0015: B2  getstatic 11 REDApp.tags : [LREDApp$Tag;
 0018: BE  arraylength
 0019: A2  if_icmpge 0037
 001C: B2  getstatic 11 REDApp.tags : [LREDApp$Tag;
 001F: 15  iload 10
 0021: 32  aaload
 0022: B4  getfield 14 REDApp$Tag.isTagValid : Z
 0025: 9A  ifne 002D
 0028: 15  iload 9
 002A: 06  iconst_3
 002B: 68  imul
 002C: AC  ireturn
 002D: 15  iload 10
 002F: 04  iconst_1
 0030: 60  iadd
 0031: 91  i2b
 0032: 36  istore 10
 0034: A7  goto 0013
 0037: 15  iload 9
 0039: AC  ireturn

Method: REDApp.getTagIndex : (BZ)B

MaxStack ............... 2
MaxLocals .............. 3
Access Flags ........... a
Code Size .............. 40

 0000: 1B  iload_1
 0001: 9A  ifne 0006
 0004: 03  iconst_0
 0005: AC  ireturn
 0006: 04  iconst_1
 0007: 3D  istore_2
 0008: 1C  iload_2
 0009: B2  getstatic 11 REDApp.tags : [LREDApp$Tag;
 000C: BE  arraylength
 000D: A2  if_icmpge 0026
 0010: B2  getstatic 11 REDApp.tags : [LREDApp$Tag;
 0013: 1C  iload_2
 0014: 32  aaload
 0015: B4  getfield 19 REDApp$Tag.tagNo : B
 0018: 1A  iload_0
 0019: A0  if_icmpne 001E
 001C: 1C  iload_2
 001D: AC  ireturn
 001E: 1C  iload_2
 001F: 04  iconst_1
 0020: 60  iadd
 0021: 91  i2b
 0022: 3D  istore_2
 0023: A7  goto 0008
 0026: 02  iconst_m1
 0027: AC  ireturn

Method: REDApp.<clinit> : ()V

MaxStack ............... 5
MaxLocals .............. 0
Access Flags ........... 88
Code Size .............. 566

 0000: 10  bipush 72
 0002: BC  newarray 8
 0004: 59  dup
 0005: 03  iconst_0
 0006: 08  iconst_5
 0007: 54  bastore
 0008: 59  dup
 0009: 04  iconst_1
 000A: 10  bipush 159
 000C: 54  bastore
 000D: 59  dup
 000E: 05  iconst_2
 000F: 10  bipush 43
 0011: 54  bastore
 0012: 59  dup
 0013: 06  iconst_3
 0014: 10  bipush 38
 0016: 54  bastore
 0017: 59  dup
 0018: 07  iconst_4
 0019: 10  bipush 94
 001B: 54  bastore
 001C: 59  dup
 001D: 08  iconst_5
 001E: 10  bipush 164
 0020: 54  bastore
 0021: 59  dup
 0022: 10  bipush 6
 0024: 10  bipush 188
 0026: 54  bastore
 0027: 59  dup
 0028: 10  bipush 7
 002A: 10  bipush 48
 002C: 54  bastore
 002D: 59  dup
 002E: 10  bipush 8
 0030: 10  bipush 129
 0032: 54  bastore
 0033: 59  dup
 0034: 10  bipush 9
 0036: 10  bipush 44
 0038: 54  bastore
 0039: 59  dup
 003A: 10  bipush 10
 003C: 10  bipush 52
 003E: 54  bastore
 003F: 59  dup
 0040: 10  bipush 11
 0042: 10  bipush 61
 0044: 54  bastore
 0045: 59  dup
 0046: 10  bipush 12
 0048: 10  bipush 38
 004A: 54  bastore
 004B: 59  dup
 004C: 10  bipush 13
 004E: 10  bipush 63
 0050: 54  bastore
 0051: 59  dup
 0052: 10  bipush 14
 0054: 10  bipush 227
 0056: 54  bastore
 0057: 59  dup
 0058: 10  bipush 15
 005A: 10  bipush 234
 005C: 54  bastore
 005D: 59  dup
 005E: 10  bipush 16
 0060: 10  bipush 34
 0062: 54  bastore
 0063: 59  dup
 0064: 10  bipush 17
 0066: 10  bipush 87
 0068: 54  bastore
 0069: 59  dup
 006A: 10  bipush 18
 006C: 10  bipush 157
 006E: 54  bastore
 006F: 59  dup
 0070: 10  bipush 19
 0072: 10  bipush 153
 0074: 54  bastore
 0075: 59  dup
 0076: 10  bipush 20
 0078: 10  bipush 30
 007A: 54  bastore
 007B: 59  dup
 007C: 10  bipush 21
 007E: 10  bipush 239
 0080: 54  bastore
 0081: 59  dup
 0082: 10  bipush 22
 0084: 10  bipush 37
 0086: 54  bastore
 0087: 59  dup
 0088: 10  bipush 23
 008A: 10  bipush 127
 008C: 54  bastore
 008D: 59  dup
 008E: 10  bipush 24
 0090: 10  bipush 171
 0092: 54  bastore
 0093: 59  dup
 0094: 10  bipush 25
 0096: 10  bipush 234
 0098: 54  bastore
 0099: 59  dup
 009A: 10  bipush 26
 009C: 10  bipush 251
 009E: 54  bastore
 009F: 59  dup
 00A0: 10  bipush 27
 00A2: 10  bipush 235
 00A4: 54  bastore
 00A5: 59  dup
 00A6: 10  bipush 28
 00A8: 10  bipush 131
 00AA: 54  bastore
 00AB: 59  dup
 00AC: 10  bipush 29
 00AE: 10  bipush 240
 00B0: 54  bastore
 00B1: 59  dup
 00B2: 10  bipush 30
 00B4: 10  bipush 242
 00B6: 54  bastore
 00B7: 59  dup
 00B8: 10  bipush 31
 00BA: 10  bipush 86
 00BC: 54  bastore
 00BD: 59  dup
 00BE: 10  bipush 32
 00C0: 10  bipush 241
 00C2: 54  bastore
 00C3: 59  dup
 00C4: 10  bipush 33
 00C6: 10  bipush 201
 00C8: 54  bastore
 00C9: 59  dup
 00CA: 10  bipush 34
 00CC: 10  bipush 60
 00CE: 54  bastore
 00CF: 59  dup
 00D0: 10  bipush 35
 00D2: 10  bipush 54
 00D4: 54  bastore
 00D5: 59  dup
 00D6: 10  bipush 36
 00D8: 03  iconst_0
 00D9: 54  bastore
 00DA: 59  dup
 00DB: 10  bipush 37
 00DD: 10  bipush 36
 00DF: 54  bastore
 00E0: 59  dup
 00E1: 10  bipush 38
 00E3: 10  bipush 9
 00E5: 54  bastore
 00E6: 59  dup
 00E7: 10  bipush 39
 00E9: 10  bipush 48
 00EB: 54  bastore
 00EC: 59  dup
 00ED: 10  bipush 40
 00EF: 10  bipush 189
 00F1: 54  bastore
 00F2: 59  dup
 00F3: 10  bipush 41
 00F5: 10  bipush 30
 00F7: 54  bastore
 00F8: 59  dup
 00F9: 10  bipush 42
 00FB: 10  bipush 93
 00FD: 54  bastore
 00FE: 59  dup
 00FF: 10  bipush 43
 0101: 10  bipush 231
 0103: 54  bastore
 0104: 59  dup
 0105: 10  bipush 44
 0107: 10  bipush 222
 0109: 54  bastore
 010A: 59  dup
 010B: 10  bipush 45
 010D: 10  bipush 50
 010F: 54  bastore
 0110: 59  dup
 0111: 10  bipush 46
 0113: 10  bipush 253
 0115: 54  bastore
 0116: 59  dup
 0117: 10  bipush 47
 0119: 10  bipush 86
 011B: 54  bastore
 011C: 59  dup
 011D: 10  bipush 48
 011F: 10  bipush 174
 0121: 54  bastore
 0122: 59  dup
 0123: 10  bipush 49
 0125: 02  iconst_m1
 0126: 54  bastore
 0127: 59  dup
 0128: 10  bipush 50
 012A: 10  bipush 184
 012C: 54  bastore
 012D: 59  dup
 012E: 10  bipush 51
 0130: 10  bipush 8
 0132: 54  bastore
 0133: 59  dup
 0134: 10  bipush 52
 0136: 10  bipush 47
 0138: 54  bastore
 0139: 59  dup
 013A: 10  bipush 53
 013C: 10  bipush 134
 013E: 54  bastore
 013F: 59  dup
 0140: 10  bipush 54
 0142: 10  bipush 199
 0144: 54  bastore
 0145: 59  dup
 0146: 10  bipush 55
 0148: 10  bipush 113
 014A: 54  bastore
 014B: 59  dup
 014C: 10  bipush 56
 014E: 10  bipush 60
 0150: 54  bastore
 0151: 59  dup
 0152: 10  bipush 57
 0154: 10  bipush 64
 0156: 54  bastore
 0157: 59  dup
 0158: 10  bipush 58
 015A: 10  bipush 142
 015C: 54  bastore
 015D: 59  dup
 015E: 10  bipush 59
 0160: 10  bipush 39
 0162: 54  bastore
 0163: 59  dup
 0164: 10  bipush 60
 0166: 10  bipush 33
 0168: 54  bastore
 0169: 59  dup
 016A: 10  bipush 61
 016C: 10  bipush 36
 016E: 54  bastore
 016F: 59  dup
 0170: 10  bipush 62
 0172: 10  bipush 186
 0174: 54  bastore
 0175: 59  dup
 0176: 10  bipush 63
 0178: 10  bipush 110
 017A: 54  bastore
 017B: 59  dup
 017C: 10  bipush 64
 017E: 10  bipush 137
 0180: 54  bastore
 0181: 59  dup
 0182: 10  bipush 65
 0184: 10  bipush 67
 0186: 54  bastore
 0187: 59  dup
 0188: 10  bipush 66
 018A: 10  bipush 193
 018C: 54  bastore
 018D: 59  dup
 018E: 10  bipush 67
 0190: 10  bipush 185
 0192: 54  bastore
 0193: 59  dup
 0194: 10  bipush 68
 0196: 10  bipush 40
 0198: 54  bastore
 0199: 59  dup
 019A: 10  bipush 69
 019C: 10  bipush 235
 019E: 54  bastore
 019F: 59  dup
 01A0: 10  bipush 70
 01A2: 10  bipush 14
 01A4: 54  bastore
 01A5: 59  dup
 01A6: 10  bipush 71
 01A8: 10  bipush 181
 01AA: 54  bastore
 01AB: B3  putstatic 17 REDApp.PubKS : [B
 01AE: 10  bipush 9
 01B0: BD  anewarray 28 REDApp$Tag
 01B3: 59  dup
 01B4: 03  iconst_0
 01B5: BB  new 28 REDApp$Tag
 01B8: 59  dup
 01B9: B7  invokespecial 29 REDApp$Tag.<init> : ()V
 01BC: 53  aastore
 01BD: 59  dup
 01BE: 04  iconst_1
 01BF: BB  new 28 REDApp$Tag
 01C2: 59  dup
 01C3: B7  invokespecial 29 REDApp$Tag.<init> : ()V
 01C6: 53  aastore
 01C7: 59  dup
 01C8: 05  iconst_2
 01C9: BB  new 28 REDApp$Tag
 01CC: 59  dup
 01CD: B7  invokespecial 29 REDApp$Tag.<init> : ()V
 01D0: 53  aastore
 01D1: 59  dup
 01D2: 06  iconst_3
 01D3: BB  new 28 REDApp$Tag
 01D6: 59  dup
 01D7: B7  invokespecial 29 REDApp$Tag.<init> : ()V
 01DA: 53  aastore
 01DB: 59  dup
 01DC: 07  iconst_4
 01DD: BB  new 28 REDApp$Tag
 01E0: 59  dup
 01E1: B7  invokespecial 29 REDApp$Tag.<init> : ()V
 01E4: 53  aastore
 01E5: 59  dup
 01E6: 08  iconst_5
 01E7: BB  new 28 REDApp$Tag
 01EA: 59  dup
 01EB: B7  invokespecial 29 REDApp$Tag.<init> : ()V
 01EE: 53  aastore
 01EF: 59  dup
 01F0: 10  bipush 6
 01F2: BB  new 28 REDApp$Tag
 01F5: 59  dup
 01F6: B7  invokespecial 29 REDApp$Tag.<init> : ()V
 01F9: 53  aastore
 01FA: 59  dup
 01FB: 10  bipush 7
 01FD: BB  new 28 REDApp$Tag
 0200: 59  dup
 0201: B7  invokespecial 29 REDApp$Tag.<init> : ()V
 0204: 53  aastore
 0205: 59  dup
 0206: 10  bipush 8
 0208: BB  new 28 REDApp$Tag
 020B: 59  dup
 020C: B7  invokespecial 29 REDApp$Tag.<init> : ()V
 020F: 53  aastore
 0210: B3  putstatic 11 REDApp.tags : [LREDApp$Tag;
 0213: 04  iconst_1
 0214: B3  putstatic 26 REDApp.isValid : Z
 0217: 10  bipush 8
 0219: BC  newarray 8
 021B: B3  putstatic 9 REDApp.tagRandom : [B
 021E: 10  bipush 16
 0220: B3  putstatic 23 REDApp.lastTagNo : B
 0223: 03  iconst_0
 0224: B3  putstatic 27 REDApp.Slices : B
 0227: 10  bipush 28
 0229: BC  newarray 8
 022B: B3  putstatic 25 REDApp.message : [B
 022E: 10  bipush 72
 0230: BC  newarray 8
 0232: B3  putstatic 16 REDApp.signature : [B
 0235: B1  return
Generating code for: REDApp.<init> : ()V

Generating code for: REDApp.verifyTag : (BZ[B[B)Z


Loading class REDApp$Tag ...

  0001: Class - 0015
  0002: MethodRef - Class=0007, Name&Type=0016
  0003: FieldRef - Class=0006, Name&Type=0017
  0004: FieldRef - Class=0006, Name&Type=0018
  0005: FieldRef - Class=0006, Name&Type=0019
  0006: Class - 001A
  0007: Class - 001D
  0008: UTF8 - tagNo
  0009: UTF8 - B
  000A: UTF8 - tagInfo
  000B: UTF8 - [B
  000C: UTF8 - pubKC
  000D: UTF8 - tagWeight
  000E: UTF8 - I
  000F: UTF8 - tagConsumption
  0010: UTF8 - isTagValid
  0011: UTF8 - Z
  0012: UTF8 - <init>
  0013: UTF8 - ()V
  0014: UTF8 - Code
  0015: UTF8 - REDApp
  0016: Name&Type - Name=0012, Desc=0013
  0017: Name&Type - Name=0008, Desc=0009
  0018: Name&Type - Name=000A, Desc=000B
  0019: Name&Type - Name=000C, Desc=000B
  001A: UTF8 - REDApp$Tag
  001B: UTF8 - Tag
  001C: UTF8 - InnerClasses
  001D: UTF8 - java/lang/Object

Class REDApp$Tag contains 6 fields.

     0 - 0000 0000 01 1  D:0000 tagNo B
     1 - 0000 8000 01 2  D:0001 tagInfo [B
     2 - 0000 8000 01 2  D:0003 pubKC [B
     3 - 0000 0000 04 4  D:0005 tagWeight I
     4 - 0000 0000 04 4  D:0009 tagConsumption I
     5 - 0000 0000 00 1  D:000D isTagValid Z

Method: REDApp$Tag.<init> : ()V

MaxStack ............... 2
MaxLocals .............. 1
Access Flags ........... 2000
Code Size .............. 27

 0000: 2A  aload_0
 0001: B7  invokespecial 2 java/lang/Object.<init> : ()V
 0004: 2A  aload_0
 0005: 10  bipush 127
 0007: B5  putfield 3 REDApp$Tag.tagNo : B
 000A: 2A  aload_0
 000B: 10  bipush 35
 000D: BC  newarray 8
 000F: B5  putfield 4 REDApp$Tag.tagInfo : [B
 0012: 2A  aload_0
 0013: 10  bipush 72
 0015: BC  newarray 8
 0017: B5  putfield 5 REDApp$Tag.pubKC : [B
 001A: B1  return
Generating code for: REDApp.verifyMessage : ([B[B[B)Z

Generating code for: REDApp.generateRandom : ([B)V

Generating code for: REDApp.verifyChallenge : (BZ[B)Z

Generating code for: REDApp.removeTag : (B)Z

Generating code for: REDApp.updateConsumption : (BZI[B)Z

Generating code for: REDApp.verifyWeight : (BZ[B)Z

Generating code for: REDApp.CNOF : (IIIII)I

Generating code for: REDApp.CEOP : (IIIIII)I

Generating code for: REDApp.CNOP : (IIIIII)I

Generating code for: REDApp.CYSO : (IIIIIIIII)I

Generating code for: REDApp.getTagIndex : (BZ)B

Generating code for: REDApp.<clinit> : ()V

Generating code for: REDApp$Tag.<init> : ()V

#define DEVELOPER_ID 0x0000928B

#define IMAGE_NAME   "REDApp"

unsigned char VM_vm_image_checksum[] =
{
    0xDD,0x82,0x70,0xE5,0x0F,0x22,0xA9,0x1E,0x57,0x17,0xF3,0x7F,0x6E,0x1E,0x6D,0xF5
};

unsigned char VM_vm_image[] =
{
    0xBA,0x34,0x01,0x00,0xDE,0x09,0x00,0x00,0xDD,0x82,0x70,0xE5,0x0F,0x22,0xA9,0x1E,
    0x26,0xC5,0xAE,0x8C,0x73,0x98,0x0A,0x65,0xC5,0xE2,0xBA,0x87,0x37,0x05,0xFF,0x26,
    0x15,0x46,0xE0,0xF3,0x4D,0x34,0x72,0x24,0x94,0xAB,0xD7,0x64,0xD2,0x35,0xE3,0xBD,
    0xDB,0x6A,0x3D,0xB6,0x3C,0xCC,0x5F,0x82,0xFF,0x20,0xF4,0x28,0xFD,0xA3,0x87,0x1C,
    0xE2,0xF1,0x72,0xAA,0x89,0xE4,0xE8,0x19,0xBF,0x8A,0xE2,0xAF,0xF9,0x97,0x48,0x2F,
    0x43,0xB3,0x01,0xB3,0xB8,0xEC,0xDF,0xC2,0xA4,0xA4,0x3D,0x92,0x3C,0x23,0xA3,0x23,
    0xA8,0x8C,0xDF,0xC2,0x99,0xF5,0xBC,0x99,0xB7,0xE5,0x5B,0xB4,0x60,0x82,0x89,0xF1,
    0x12,0x80,0x8B,0xB5,0x2C,0x9E,0x7E,0x55,0x3F,0xDE,0x0A,0xA7,0x99,0xAD,0x81,0x70,
    0x82,0xD4,0xA3,0xB8,0x3F,0x75,0x48,0xE3,0xE6,0x74,0xFA,0x92,0x15,0x0C,0x5F,0xFE,
    0x8A,0x55,0xE3,0x43,0xCC,0x29,0xB3,0x36,0xAE,0xBB,0xBA,0xE4,0x6B,0x3D,0xAB,0x84,
    0xB0,0x3F,0x77,0xA7,0x73,0xEA,0x88,0x72,0x39,0x8E,0x64,0xA9,0x84,0x21,0xB4,0x76,
    0xC2,0xD7,0x98,0x9F,0x06,0x49,0xD6,0x86,0x14,0xF0,0xC4,0xB2,0x05,0xBD,0xCB,0x15,
    0x73,0x8B,0x1E,0x93,0x7F,0xA6,0x9A,0xD2,0x0D,0x83,0xAD,0xE5,0x27,0x81,0x1E,0xA3,
    0x7E,0x34,0xE0,0x46,0xB8,0x2F,0xA8,0x90,0x14,0xB1,0xAD,0xBB,0xC9,0x07,0xFB,0xFD,
    0xB4,0xBB,0x42,0x45,0x65,0x57,0x42,0x77,0x62,0xA7,0x2F,0xE4,0x96,0x88,0xE7,0x2C,
    0x9D,0x5A,0xAB,0x58,0x2D,0xA5,0x4C,0xF8,0xCE,0x97,0x0F,0xC3,0x3E,0xA4,0x26,0xEB,
    0x95,0x4A,0x01,0x8B,0x0A,0x31,0x4B,0x4B,0x7D,0x1E,0x6D,0x5D,0x18,0xD5,0xF8,0x6C,
    0x39,0xE0,0x74,0x42,0xD5,0x85,0x35,0x53,0x46,0xCA,0xAE,0x0A,0xC5,0xCE,0x0D,0xE9,
    0x43,0x6F,0xD5,0xE6,0xB1,0x9F,0xB5,0x3F,0xE5,0x00,0xFC,0x2D,0x77,0x4A,0x01,0xF9,
    0x49,0x09,0xF3,0x78,0x7B,0xD8,0x4B,0x7F,0x5F,0xA5,0x49,0x34,0xE2,0x80,0xFD,0xCB,
    0xFC,0xDE,0xF8,0x3D,0x3B,0x27,0x47,0x53,0x27,0xD0,0x4B,0x60,0x75,0x60,0xFC,0x47,
    0x4A,0x30,0x05,0xEB,0x28,0x05,0x00,0xD5,0x5B,0x21,0x70,0x32,0x72,0xC6,0x3B,0xD1,
    0x97,0x49,0x43,0x94,0x9B,0xEE,0xB5,0x4A,0xE1,0x97,0xED,0xE8,0xC3,0x3C,0x67,0xBF,
    0x43,0xE5,0xC3,0xFF,0x70,0xF4,0x8C,0xD2,0x05,0xD5,0xCD,0xA4,0xE7,0x28,0xD6,0xB8,
    0xAC,0x6E,0x5D,0x0E,0x7C,0x9E,0x0F,0xB0,0x85,0xD2,0x57,0xA0,0xF5,0x67,0x0D,0x14,
    0x92,0xF0,0xAD,0x24,0x87,0x2B,0x07,0xCC,0x69,0xFB,0x3C,0x04,0xE6,0x7E,0x38,0x26,
    0xF5,0x78,0x37,0xAF,0x24,0x8F,0x95,0xE2,0xFA,0xAF,0x9D,0x01,0x57,0x13,0x13,0x7F,
    0x36,0xD4,0x11,0xCE,0x1E,0xDD,0xB6,0xDB,0x79,0x69,0x9A,0x25,0x45,0xDA,0xD4,0xA1,
    0xA3,0x29,0xD5,0xAB,0xE5,0x97,0x1C,0x63,0x61,0xB9,0x58,0x4F,0xB8,0xD1,0x0E,0x4C,
    0x00,0x65,0x41,0x69,0x59,0xD0,0x3F,0x21,0x05,0x75,0xD0,0xEE,0x9E,0x24,0xBA,0xE2,
    0x51,0xA2,0x6D,0x77,0x9C,0x15,0x76,0xEB,0xF7,0xAB,0x1E,0x42,0x4C,0x3B,0x93,0x89,
    0x5E,0x7E,0xD3,0x7C,0xF7,0xB0,0x34,0x24,0x61,0xAA,0xB5,0x25,0x5E,0x23,0xF6,0xCA,
    0x92,0x94,0x90,0x71,0x1F,0x9D,0x6E,0x4D,0x7F,0xB5,0xE7,0xFF,0x6A,0xA7,0xB4,0x77,
    0x7C,0x3D,0x93,0x05,0xBB,0x29,0x08,0x6B,0x7B,0xA6,0x44,0xBB,0x1C,0x50,0x41,0xDE,
    0xE3,0x97,0xF9,0x7F,0x97,0xA1,0x70,0xA4,0x65,0x32,0xBC,0xEC,0x98,0xA4,0xF6,0x51,
    0x3F,0xA4,0xFF,0x01,0x1C,0x80,0xB7,0x7E,0x6E,0xCC,0x02,0x74,0x0E,0x6B,0x4D,0xC0,
    0x66,0x0A,0xF8,0x38,0x26,0xFC,0x7B,0x64,0x9E,0x55,0x9A,0xBC,0x84,0x05,0x59,0xE8,
    0xB6,0x7F,0x63,0x7E,0xAE,0x73,0xD0,0x36,0x9E,0x90,0x9F,0x62,0xBC,0x30,0x52,0x4E,
    0x94,0x0C,0x04,0x6B,0x12,0x10,0xEF,0x3D,0x4A,0x46,0xDC,0x2E,0x3A,0x7E,0xF6,0x28,
    0xB1,0xFD,0xE5,0x13,0x55,0x7C,0xB9,0xCC,0x91,0x9A,0xBD,0xB1,0xAC,0x89,0xC7,0x16,
    0xA8,0xEF,0x84,0xD9,0x9C,0x75,0x25,0x6F,0xCB,0xF9,0x8B,0xDB,0xDB,0x60,0x6B,0x42,
    0x77,0xC0,0x81,0x2D,0x02,0x0D,0x32,0x54,0x71,0xD2,0x44,0x72,0xA7,0x99,0xB8,0x4F,
    0xF3,0x29,0xF4,0x3D,0xD8,0xF6,0x20,0xF9,0x5A,0x56,0x07,0xED,0x85,0xD6,0x30,0x2A,
    0x64,0xE0,0x3B,0x4B,0x0B,0x6F,0x45,0x71,0x08,0x1F,0x8B,0xB6,0x15,0x8A,0x1B,0x26,
    0x4E,0x85,0x9F,0x2E,0xB6,0x9E,0xE6,0xE7,0xAE,0xEB,0x3F,0xE8,0x1F,0x9D,0x5D,0x90,
    0x20,0x3D,0x07,0x0E,0x3F,0x85,0x26,0x46,0x7E,0xA2,0x82,0x97,0xBA,0x28,0xC1,0x57,
    0x95,0xD8,0xF4,0x72,0x7E,0x2A,0x0D,0x30,0x47,0x54,0xF2,0xC2,0xBE,0x4F,0x2A,0xD9,
    0x3C,0x3F,0xD7,0x2E,0xAA,0xD4,0xBC,0xB2,0x7F,0x57,0xA8,0x76,0xDC,0x02,0x0F,0x8B,
    0xE8,0x74,0x62,0x73,0xAD,0x4E,0xF5,0xFF,0x9B,0x8D,0xEE,0x97,0x80,0xF7,0x3C,0xD7,
    0x26,0x4C,0x2E,0xEE,0x6F,0xBA,0xB9,0xFD,0x04,0x97,0xAA,0x38,0xE6,0x89,0xD7,0x63,
    0x49,0x11,0x29,0x2A,0x7D,0x9D,0x9D,0x6F,0xAA,0x79,0xB1,0x09,0xF5,0xBA,0x78,0xB9,
    0x3F,0x59,0x86,0x37,0xFB,0x0F,0x5E,0x45,0xC1,0x6E,0xB1,0xC0,0x3C,0x85,0xE2,0xDF,
    0x83,0xE7,0xFF,0x38,0x99,0x28,0xE7,0x60,0x91,0xCD,0x14,0xD4,0xB9,0x58,0x78,0xEA,
    0x38,0x78,0x53,0x3D,0x8C,0xEA,0xB3,0xC0,0x74,0xD9,0xB0,0x5D,0xDA,0x06,0xAC,0xE9,
    0xBA,0xF8,0xA2,0xAC,0x3D,0x84,0xE0,0xCB,0x90,0xEC,0xE9,0xA2,0x23,0x85,0x23,0xF0,
    0x80,0x69,0xD4,0x42,0xD7,0xA4,0xF1,0x34,0x9E,0xB6,0x21,0x3C,0x32,0x41,0x35,0x5A,
    0x56,0xAF,0x67,0x7C,0x53,0xFD,0x56,0x94,0x6D,0x65,0x61,0xDF,0x2E,0x01,0x29,0x79,
    0x34,0x10,0x5A,0xB4,0x8D,0x3A,0x2A,0x90,0x5E,0x43,0xD7,0x8C,0x72,0xB3,0xCA,0x3A,
    0xAD,0x32,0xCE,0xBE,0x28,0xF1,0x47,0xEF,0xC5,0x13,0x95,0xE9,0x81,0x88,0x2A,0x52,
    0x88,0xB1,0xE0,0x84,0x3D,0x42,0x4E,0xE0,0x09,0x9C,0x39,0x2F,0xAF,0x66,0x6F,0xE3,
    0xE7,0x46,0x9A,0x0D,0x17,0xA0,0x3F,0x4D,0xCF,0x7E,0xA4,0x3F,0x8A,0x51,0xCE,0x8C,
    0x2E,0x40,0x93,0x57,0xF6,0x87,0x8F,0x7F,0x84,0xAF,0xD4,0x67,0x68,0x72,0x07,0xD5,
    0xEC,0xC2,0x69,0xF2,0x9A,0xE3,0x73,0xF5,0xE6,0xC0,0x19,0x1F,0xBD,0xC5,0xD7,0x2C,
    0xCB,0x56,0x16,0xBF,0xCC,0x00,0x13,0x6B,0xD6,0x52,0x0C,0x12,0x4B,0xEB,0xE6,0xF2,
    0x7D,0x3A,0xC4,0xBA,0xD1,0xC3,0xEC,0x29,0x32,0xEA,0xF0,0xCB,0xAB,0x0C,0x60,0x7E,
    0xCE,0x9B,0x74,0xB5,0xBF,0x1D,0xF9,0x8C,0x20,0xF3,0xC3,0x8D,0x7F,0xB6,0xC3,0x25,
    0x77,0x95,0x7B,0xED,0xA9,0xA1,0x5A,0x7D,0x32,0x6C,0x05,0x8A,0x44,0xAB,0xF5,0xA3,
    0xCF,0xA5,0x4E,0x11,0xC0,0x2A,0xAD,0x89,0x0A,0x69,0xE7,0xF2,0x42,0xAE,0x20,0x00,
    0x50,0x39,0xE7,0xC7,0xB0,0x33,0xB8,0x0F,0x3C,0x00,0xE9,0x8D,0xFB,0x80,0xC5,0x96,
    0xD8,0x2B,0x36,0x1A,0xC1,0x1B,0x38,0x07,0xFB,0x1A,0x93,0xD1,0xCF,0x84,0x18,0xE5,
    0x62,0x86,0xCB,0xCB,0xDF,0xAB,0x2C,0x6D,0x71,0x4F,0xF6,0x11,0xB1,0xFF,0x84,0x77,
    0x64,0x6D,0xB8,0x09,0xED,0xD9,0x8B,0x4A,0x96,0x7B,0x01,0x90,0xDF,0xEB,0x58,0x40,
    0xB0,0xEC,0xC1,0x28,0x69,0xEA,0x00,0xA7,0xF1,0xF2,0xD3,0xCA,0x7B,0x42,0x34,0x1C,
    0x28,0x8F,0x57,0xF1,0x9A,0x08,0x8E,0x8D,0xC5,0x24,0x9E,0x9E,0x4C,0x16,0xA4,0xD9,
    0x89,0x7A,0x00,0xA2,0x77,0xF1,0xC5,0xDD,0x49,0x60,0x7E,0x90,0xB9,0x70,0xEF,0x94,
    0x1F,0x25,0x85,0xA6,0x45,0xF8,0x54,0xE4,0x59,0x17,0x60,0x68,0xCD,0x86,0x5F,0x03,
    0xA8,0xAB,0xB9,0x22,0xB1,0x8A,0x70,0xA2,0x9F,0xDC,0x2D,0x58,0x5E,0x3C,0x0D,0x1A,
    0x34,0x6A,0x15,0x2E,0x71,0x44,0xE5,0x5D,0x64,0xBC,0x66,0x57,0xEB,0xB1,0xD2,0xC2,
    0x62,0xE7,0x33,0xE8,0xFB,0x52,0x35,0xD5,0x87,0x0B,0x14,0x4A,0x28,0x99,0x02,0x60,
    0x05,0xED,0x6D,0xA6,0xAA,0xA7,0x6D,0x19,0xBE,0x5A,0xC1,0xEE,0xCB,0xB3,0xDA,0x3A,
    0x5C,0x6F,0xD9,0x80,0x4A,0x78,0x41,0xC6,0x78,0x04,0x57,0x1B,0x19,0x44,0x04,0x30,
    0x48,0xD6,0x79,0xEF,0xC9,0x7E,0xCF,0xC0,0x65,0xDF,0xA7,0x01,0x2C,0xA9,0x6E,0xA9,
    0x23,0x25,0x48,0xA3,0x88,0x78,0x81,0x6E,0x05,0xEE,0x2C,0x77,0x81,0xDF,0x41,0x6E,
    0x1F,0xF6,0x77,0x6E,0xA4,0x2D,0x58,0xC8,0xA2,0x2F,0x2A,0x45,0x5E,0x35,0x13,0x7C,
    0x15,0xBD,0x6E,0xDD,0x58,0xC8,0x1A,0x11,0x18,0x97,0x3A,0xF4,0xBB,0x57,0xAA,0x59,
    0x9F,0x82,0x94,0xC5,0xB8,0xEC,0xA8,0x9C,0x74,0x25,0xC9,0xE5,0xB8,0xEB,0x5A,0xA4,
    0xF7,0x45,0xE5,0xD7,0x1B,0xDA,0x92,0x7F,0x51,0xDC,0x0E,0xED,0xE4,0x17,0x83,0x24,
    0x14,0xDC,0xE2,0x3F,0x0C,0xC6,0x0A,0x0C,0x5B,0x7C,0xFE,0xC8,0x06,0xEA,0x8B,0xC3,
    0xBB,0xCA,0x00,0x5F,0xFD,0xD9,0xD6,0xA4,0xFB,0x4B,0xC7,0x07,0x27,0xE3,0x81,0x92,
    0xCC,0xA0,0xEF,0x4F,0xEA,0x4F,0x54,0xB2,0x1B,0x86,0x7E,0x25,0x9B,0x60,0x2D,0x88,
    0xBB,0x6A,0x86,0x50,0x07,0x10,0x32,0x87,0x4D,0x87,0x36,0x62,0xC2,0x8D,0xE6,0xE6,
    0xF7,0x0A,0xD3,0x08,0x2D,0x4E,0xD5,0x20,0xE9,0x17,0xE9,0xD2,0x2F,0xB6,0x3E,0x34,
    0xA0,0x51,0xF6,0xDF,0x02,0xD4,0x9D,0xD0,0xF1,0xC0,0x38,0x7C,0x39,0x3F,0x2C,0x9F,
    0x0F,0xF1,0x60,0xCB,0xA2,0x33,0xA0,0x4B,0xF5,0x19,0x16,0x12,0xFB,0xD2,0x23,0x37,
    0x69,0x7F,0xFF,0xF2,0xDB,0x44,0xDC,0xDA,0x58,0x0C,0x85,0xAF,0xDC,0x44,0x17,0xC8,
    0x46,0xA2,0xEF,0x27,0x4A,0xE1,0xF5,0xB8,0xEA,0xF3,0x81,0xE6,0xA2,0x0A,0xA9,0x70,
    0xEC,0xC1,0xAD,0x24,0x22,0x18,0x2C,0x4F,0xB1,0x88,0x37,0xB9,0xE2,0x18,0x8A,0xCB,
    0x7E,0x90,0x62,0xB6,0x20,0x55,0x7D,0xBE,0xBD,0x78,0x2C,0x62,0x5C,0xF5,0x51,0xC9,
    0xA0,0x90,0x90,0xA4,0x3A,0x78,0xBA,0x49,0x6B,0xF6,0xCA,0xF5,0xE5,0xC4,0x04,0xC4,
    0xF9,0xC2,0xDC,0x28,0x9E,0x62,0xD5,0x7B,0x7B,0x76,0xCF,0xB5,0x2A,0x7C,0xEF,0x1F,
    0xEF,0x56,0x74,0x4B,0x6F,0xC1,0x72,0x30,0x69,0x34,0xEC,0x5B,0x0F,0x0F,0x7E,0x34,
    0x16,0x9B,0xF0,0x5B,0x49,0x69,0x19,0x59,0xA7,0x6F,0x50,0x28,0xF0,0xC4,0x37,0x64,
    0xD1,0xAC,0xF6,0x76,0x71,0x98,0xFF,0x10,0xDD,0x64,0x73,0x44,0xF7,0xAD,0xE2,0xA2,
    0x77,0xF5,0x0F,0xFD,0xC8,0x50,0xAC,0xA2,0x53,0x61,0x03,0x38,0xAF,0xBB,0xDF,0x1B,
    0x37,0xF4,0x32,0xC1,0x0C,0x44,0x07,0x3D,0x16,0x8E,0x13,0xAD,0x8D,0x6E,0x52,0xAB,
    0x6C,0x37,0x05,0xBE,0xED,0xE4,0xAE,0xFF,0x0D,0x62,0x59,0x9D,0xA8,0x56,0x8A,0xFF,
    0xBC,0xE9,0xA4,0x5A,0x78,0x65,0x27,0xF3,0x0F,0x76,0xF6,0x2D,0x7C,0xF3,0x57,0x75,
    0xEB,0x8F,0x87,0x70,0x1D,0x35,0xC1,0x00,0x73,0xB9,0x1C,0x53,0x7F,0xD9,0xDA,0x70,
    0x13,0xAE,0xF0,0xFF,0xC2,0x6A,0xE3,0x50,0x37,0xFA,0x93,0xAC,0xB0,0x2A,0x32,0x57,
    0xE2,0xE1,0xE1,0x8D,0x71,0x38,0xBA,0x49,0x7D,0x4A,0xB0,0x75,0x53,0x42,0x30,0xF1,
    0xF9,0x33,0x95,0xF5,0x55,0x85,0xA9,0x75,0x6E,0xA6,0x59,0x72,0x65,0xEC,0x4A,0x6C,
    0x60,0xD6,0x7F,0x4A,0x19,0xB7,0xE9,0x6F,0x3E,0x52,0xA6,0x1B,0x54,0x77,0x65,0xEF,
    0xE4,0xB6,0xF6,0x01,0xF8,0xD4,0xB9,0xCB,0x9B,0xDF,0x89,0x02,0x45,0x7E,0x5D,0xC1,
    0x8D,0x83,0x76,0x58,0x76,0x39,0xE8,0xE7,0x47,0x18,0xE6,0x2C,0x3A,0xC7,0xED,0x80,
    0xA9,0x27,0x5E,0xAF,0xC7,0xA6,0xCA,0xAB,0xD6,0x53,0x87,0x49,0xA3,0x85,0x56,0x9A,
    0xBB,0xA4,0xB5,0x7E,0x02,0x7D,0x86,0x78,0x67,0xD3,0xDB,0x07,0x13,0x88,0x00,0x4F,
    0x11,0x1C,0x9E,0xC1,0xFF,0x2E,0x46,0x10,0xA4,0xFD,0xC1,0x78,0x76,0x9A,0x37,0xFC,
    0x71,0xEB,0x43,0x57,0x54,0x3C,0xD1,0x1A,0xCF,0xE9,0xE9,0xF5,0xE2,0x4B,0xCF,0x0A,
    0x58,0x27,0x49,0x5A,0x81,0x73,0x14,0x98,0xA1,0x2B,0x37,0xD8,0x84,0x55,0xD9,0x46,
    0xC2,0x13,0xF8,0xDD,0xC8,0x0A,0xC9,0x27,0xB9,0xD3,0x9E,0x3A,0xDB,0x27,0x7B,0x6C,
    0x71,0xA5,0x92,0xE4,0x1C,0xE1,0xAD,0xD6,0x63,0x16,0x9B,0xF1,0x16,0x8D,0x1C,0x28,
    0x4F,0x37,0x41,0xDA,0xE7,0xE8,0xC3,0xAB,0xEB,0x62,0x91,0x44,0xE6,0xE7,0xFA,0x39,
    0x8F,0x22,0xBB,0x30,0x6B,0xE2,0x84,0x1D,0x0F,0x1A,0xA3,0xEE,0xA7,0xA3,0x3D,0x05,
    0x43,0xBC,0x2D,0xF2,0xE2,0x4D,0x96,0xF7,0x59,0xDD,0x30,0xC2,0xE4,0x36,0x13,0x86,
    0xDE,0xA7,0x58,0x79,0x6C,0x5E,0xC0,0x17,0xEF,0x89,0x2B,0xED,0xF3,0x0A,0x80,0x9A,
    0xD7,0x24,0xA2,0x97,0x46,0xE7,0xFF,0x0B,0x1E,0xB4,0xA7,0xD1,0xF3,0x26,0xEF,0x91,
    0xBB,0xD8,0xEA,0xAB,0xA3,0x7C,0x6F,0xC9,0xD2,0x8C,0xCC,0x3D,0xCA,0x50,0x95,0xB9,
    0x3F,0x5C,0xA7,0xF7,0x9C,0x77,0xD0,0x3B,0x54,0x66,0x33,0x2C,0x03,0x14,0x8D,0x5D,
    0x43,0x40,0xB4,0x78,0xC9,0x0F,0x93,0xDA,0xD1,0xDA,0xAD,0xC0,0xD7,0xFF,0x19,0xE5,
    0x57,0x29,0x2C,0x71,0x27,0x22,0x19,0x63,0xCA,0x74,0x2E,0xF3,0x73,0x16,0x17,0x60,
    0x64,0x3A,0x1F,0x49,0x7F,0x48,0x54,0xE5,0xDD,0xF3,0xA4,0xA6,0x79,0x27,0xAC,0xA2,
    0x89,0x29,0x4A,0x17,0x17,0x4E,0x96,0xBD,0xD2,0x18,0x3F,0x59,0x8F,0x0D,0x6C,0x56,
    0x67,0xA7,0x19,0x54,0xB6,0x59,0xE3,0xE9,0x3A,0xC9,0xB4,0xD9,0x91,0xD6,0xCF,0x61,
    0x60,0x70,0x9A,0x44,0x70,0xB8,0xD6,0x79,0x39,0x35,0x5E,0xF5,0x2D,0xF9,0x7C,0x29,
    0x1F,0x91,0x3E,0xBA,0x9B,0x78,0x44,0xF5,0xA5,0x52,0xDF,0x7A,0x30,0x25,0xA4,0x10,
    0x48,0xB7,0xE9,0x1F,0x7D,0xC5,0x49,0x73,0x39,0x62,0x57,0xC7,0xDC,0xF2,0x16,0x85,
    0x8F,0x4C,0xBA,0x0B,0xE3,0xA3,0x2E,0xF2,0xBB,0xD1,0x64,0xEB,0x70,0x0A,0x10,0x06,
    0x87,0xD9,0x8E,0x6E,0x9A,0x62,0xCB,0x84,0x7C,0xC6,0xBB,0x95,0x80,0x68,0xB0,0xD3,
    0x2D,0x04,0xCA,0xA5,0x89,0x12,0xF1,0x7C,0xF2,0x52,0xF3,0x5C,0x0B,0xE7,0x31,0xE5,
    0x2E,0x82,0x60,0xC7,0xFB,0x09,0x84,0x3D,0xD2,0x3A,0xA7,0xD7,0xA9,0x0F,0x27,0xD0,
    0x25,0x90,0x70,0xB0,0x9A,0xC2,0x01,0xE7,0x37,0x4E,0xF7,0x47,0xE5,0x30,0xD6,0x97,
    0x13,0x95,0x98,0x76,0xFE,0x5F,0x97,0xAB,0x48,0x7C,0x1E,0x3D,0xBC,0x85,0x67,0x99,
    0xA7,0x88,0xBE,0x0C,0xC9,0x2D,0xB3,0x36,0x7A,0xC5,0x18,0x57,0x94,0x3C,0x5C,0xDB,
    0x2E,0xC6,0xB0,0xD0,0x81,0xC2,0x97,0x3A,0xA5,0x93,0x0E,0x1B,0x62,0x66,0x9C,0xE7,
    0x05,0x9B,0x94,0x73,0xA5,0xF9,0xB2,0x3D,0x92,0xA7,0x16,0xE7,0xA4,0xFA,0xF3,0xE0,
    0xD9,0x82,0xD2,0x69,0x0A,0xAF,0xC9,0xC8,0x08,0xA7,0x64,0x6D,0x3E,0xCF,0x54,0x75,
    0x56,0xE4,0xC1,0x45,0x81,0x13,0x98,0x45,0xA5,0x4A,0x3C,0xC2,0x4C,0x88,0x19,0xCF,
    0x72,0x5B,0x73,0x1C,0xC0,0xEE,0xC6,0x2F,0x39,0x90,0xBE,0x9C,0x27,0xEE,0x0F,0x0A,
    0x8F,0x6A,0x05,0x6A,0x12,0x3C,0x69,0x16,0x5D,0x8A,0xE5,0xCA,0x17,0x81,0xDC,0xAF,
    0xE0,0x39,0x33,0x83,0xBE,0xA2,0xC4,0xE0,0x22,0x2D,0xE2,0x56,0xAA,0x51,0x8B,0xA8,
    0xBC,0x3F,0x36,0xDE,0x8D,0x5A,0xCD,0x67,0xE2,0x1C,0x3B,0xB2,0xFA,0x01,0x2A,0xEE,
    0xF3,0x95,0x31,0x50,0x30,0x17,0xFF,0xC9,0x0D,0x14,0xB9,0xF3,0x2E,0xD6,0xB4,0x0C,
    0x92,0x63,0xA0,0xA0,0xF2,0x6B,0x0E,0x41,0xFA,0xE6,0xB8,0x9B,0xF5,0xD2,0xD6,0xBA,
    0xF0,0xB5,0x80,0xB7,0xEE,0x17,0x86,0x16,0xDB,0x1C,0x6E,0xE1,0xD0,0x7D,0xB4,0xA0,
    0xD3,0xA9,0x41,0x04,0x83,0x88,0xDB,0xCD,0xA6,0x49,0x2C,0x64,0x1E,0x5B,0x4F,0xAA,
    0x56,0x70,0xF1,0xDB,0x39,0x2C,0xB0,0x21,0xF9,0xF3,0x07,0x22,0xCA,0x37,0x6C,0x28,
    0xF4,0x6A,0xB7,0xB9,0x3D,0xA7,0x1D,0x6D,0xF0,0x25,0x54,0x6D,0x39,0xD6,0x07,0xCF,
    0x14,0x1B,0x7F,0x90,0x88,0x77,0x49,0xAA,0x60,0x03,0x2A,0xA6,0xEF,0xA6,0xD8,0x8D,
    0x09,0x06,0x08,0x00,0x02,0x02,0x02,0x02,0x02,0x02,0x02,0x02,0x02,0x01
};

Image checksum: 0xDD8270E50F22A91E5717F37F6E1E6DF5
